quantcdn/__init__.py
quantcdn/__version__.py
quantcdn/api_client.py
quantcdn/api_response.py
quantcdn/configuration.py
quantcdn/exceptions.py
quantcdn/py.typed
quantcdn/rest.py
quantcdn/api/__init__.py
quantcdn/api/ai_agents_api.py
quantcdn/api/ai_custom_tools_api.py
quantcdn/api/ai_inference_api.py
quantcdn/api/ai_models_api.py
quantcdn/api/ai_monitoring_api.py
quantcdn/api/ai_sessions_api.py
quantcdn/api/ai_tools_api.py
quantcdn/api/ai_vector_database_api.py
quantcdn/api/applications_api.py
quantcdn/api/backup_management_api.py
quantcdn/api/commands_api.py
quantcdn/api/compose_api.py
quantcdn/api/containers_api.py
quantcdn/api/crawler_schedules_api.py
quantcdn/api/crawlers_api.py
quantcdn/api/cron_api.py
quantcdn/api/domains_api.py
quantcdn/api/environments_api.py
quantcdn/api/headers_api.py
quantcdn/api/kv_api.py
quantcdn/api/organizations_api.py
quantcdn/api/projects_api.py
quantcdn/api/purge_api.py
quantcdn/api/rules_api.py
quantcdn/api/scaling_policy_api.py
quantcdn/api/ssh_access_api.py
quantcdn/api/variables_api.py
quantcdn/api/volumes_api.py
quantcdn/models/__init__.py
quantcdn/models/application.py
quantcdn/models/application_database.py
quantcdn/models/application_deployment_information_inner.py
quantcdn/models/application_environments_inner.py
quantcdn/models/application_filesystem.py
quantcdn/models/application_image_reference.py
quantcdn/models/bulk_set_environment_variables_request.py
quantcdn/models/bulk_set_environment_variables_request_environment_inner.py
quantcdn/models/chat_inference200_response.py
quantcdn/models/chat_inference200_response_response.py
quantcdn/models/chat_inference200_response_response_tool_use.py
quantcdn/models/chat_inference200_response_response_tool_use_one_of.py
quantcdn/models/chat_inference200_response_response_tool_use_one_of1_inner.py
quantcdn/models/chat_inference200_response_response_tool_use_one_of_result.py
quantcdn/models/chat_inference200_response_usage.py
quantcdn/models/chat_inference_request.py
quantcdn_client-4.8.0.dist-info/METADATA
quantcdn_client-4.8.0.dist-info/WHEEL
quantcdn_client-4.8.0.dist-info/top_level.txt
quantcdn_client-4.8.0.dist-info/RECORD
